LICENSE
README.md
setup.py
django_germanium.egg-info/PKG-INFO
django_germanium.egg-info/SOURCES.txt
django_germanium.egg-info/dependency_links.txt
django_germanium.egg-info/not-zip-safe
django_germanium.egg-info/requires.txt
django_germanium.egg-info/top_level.txt
germanium/__init__.py
germanium/config.py
germanium/crawler.py
germanium/decorators.py
germanium/patch.py
germanium/signals.py
germanium/storage.py
germanium/sugar.py
germanium/django/__init__.py
germanium/django/runner.py
germanium/django/utils.py
germanium/test_cases/__init__.py
germanium/test_cases/auth.py
germanium/test_cases/client.py
germanium/test_cases/default.py
germanium/test_cases/migrations.py
germanium/test_cases/models.py
germanium/test_cases/rest.py
germanium/tools/__init__.py
germanium/tools/django.py
germanium/tools/http.py
germanium/tools/models.py
germanium/tools/rest.py
germanium/tools/trivials.py