Metadata-Version: 1.1
Name: django-germanium
Version: 2.3.5
Summary: Helpful methods for Python Selenium and REST testing
Home-page: UNKNOWN
Author: Lukas Rychtecky, Lubos Matl
Author-email: lukas.rychtecky@gmail.com, matllubos@gmail.com
License: UNKNOWN
Platform: UNKNOWN
Classifier: Development Status :: 3 - Alpha
Classifier: Intended Audience :: Developers
Classifier: License :: OSI Approved :: MIT License
Classifier: Operating System :: OS Independent
Classifier: Programming Language :: Python
